naunet/__init__.py
naunet/auxiliary.py
naunet/chemistry/__init__.py
naunet/chemistry/periodictable.csv
naunet/console/__init__.py
naunet/console/application.py
naunet/console/commands/__init__.py
naunet/console/commands/command.py
naunet/console/commands/example.py
naunet/console/commands/init.py
naunet/console/commands/render.py
naunet/dusts/__init__.py
naunet/dusts/dust.py
naunet/dusts/unidust.py
naunet/examples/__init__.py
naunet/examples/deuterium/__init__.py
naunet/examples/deuterium/deuterium.krome
naunet/examples/deuterium/test/CMakeLists.txt
naunet/examples/deuterium/test/parallel.cpp
naunet/examples/deuterium/test/singlegrid.cpp
naunet/examples/deuterium/test/timeres.dat
naunet/examples/ism/__init__.py
naunet/examples/ism/test/CMakeLists.txt
naunet/examples/ism/test/parallel.cpp
naunet/examples/ism/test/singlegrid.cpp
naunet/network.py
naunet/patchmaker.py
naunet/reactions/__init__.py
naunet/reactions/kidareaction.py
naunet/reactions/kromereaction.py
naunet/reactions/leedsreaction.py
naunet/reactions/reaction.py
naunet/reactions/umistreaction.py
naunet/species.py
naunet/templateloader.py
naunet/templates/cvode/CMakeLists.txt.j2
naunet/templates/cvode/include/naunet.h.j2
naunet/templates/cvode/include/naunet_constants.h.j2
naunet/templates/cvode/include/naunet_macros.h.j2
naunet/templates/cvode/include/naunet_ode.h.j2
naunet/templates/cvode/include/naunet_physics.h.j2
naunet/templates/cvode/include/naunet_timer.h
naunet/templates/cvode/include/naunet_userdata.h.j2
naunet/templates/cvode/src/CMakeLists.txt.j2
naunet/templates/cvode/src/naunet.cpp.j2
naunet/templates/cvode/src/naunet_constants.cpp.j2
naunet/templates/cvode/src/naunet_ode.cpp.j2
naunet/templates/cvode/src/naunet_physics.cpp.j2
naunet/templates/data/COshielding_11.2bH2_5e20nH.dat.j2
naunet/templates/data/H2shielding.dat.j2
naunet/templates/data/N2shielding_11.2bH2_1e20nH.dat.j2
naunet/templates/odeint/CMakeLists.txt.j2
naunet/templates/odeint/include/naunet.h.j2
naunet-0.2.0.dist-info/entry_points.txt
naunet-0.2.0.dist-info/LICENSE
naunet-0.2.0.dist-info/WHEEL
naunet-0.2.0.dist-info/METADATA
naunet-0.2.0.dist-info/RECORD
