Metadata-Version: 2.1
Name: naunet
Version: 0.2.0
Summary: 
License: GPL-3.0-or-later
Author: Chia-Jung Hsu
Author-email: appolloford@gmail.com
Requires-Python: >=3.6,<4.0
Classifier: License :: OSI Approved :: GNU General Public License v3 or later (GPLv3+)
Classifier: Programming Language :: Python :: 3
Classifier: Programming Language :: Python :: 3.6
Classifier: Programming Language :: Python :: 3.7
Classifier: Programming Language :: Python :: 3.8
Classifier: Programming Language :: Python :: 3.9
Requires-Dist: Jinja2 (>=2.11.2,<3.0.0)
Requires-Dist: cleo (>=0.8.1,<0.9.0)
Requires-Dist: lark (>=0.11.1,<0.12.0)
Requires-Dist: tomlkit (>=0.7.0,<0.8.0)
Requires-Dist: tqdm (>=4.58.0,<5.0.0)
